chainerio/__init__.py
chainerio/_context.py
chainerio/_typing.py
chainerio/container.py
chainerio/filesystem.py
chainerio/io.py
chainerio/version.py
chainerio/cache/__init__.py
chainerio/cache/file_cache.py
chainerio/cache/naive.py
chainerio/chainer_extensions/__init__.py
chainerio/chainer_extensions/snapshot.py
chainerio/chainer_extensions/snapshot_writers.py
chainerio/containers/__init__.py
chainerio/containers/zip.py
chainerio/filesystems/__init__.py
chainerio/filesystems/hdfs.py
chainerio/filesystems/posix.py
chainerio/profiler/__init__.py
chainerio/profiler/io_profiler.py
chainerio-0.1.2.dist-info/LICENSE
chainerio-0.1.2.dist-info/METADATA
chainerio-0.1.2.dist-info/WHEEL
chainerio-0.1.2.dist-info/top_level.txt
chainerio-0.1.2.dist-info/RECORD
