Metadata-Version: 2.1
Name: chainerio
Version: 0.1.2
Summary: Chainer IO library
Home-page: http://github.com/chainer/chainerio
Author: Tianqi Xu, Kota Uenishi
Author-email: tianqi@preferred.jp, kota@preferred.jp
License: UNKNOWN
Keywords: filesystem hdfs chainer development
Platform: UNKNOWN
Classifier: Development Status :: 3 - Alpha
Classifier: Intended Audience :: Developers
Classifier: Topic :: Software Development :: Build Tools
Classifier: License :: OSI Approved :: MIT License
Classifier: Operating System :: POSIX
Classifier: Operating System :: POSIX :: Linux
Classifier: Programming Language :: Python :: 3.5
Classifier: Programming Language :: Python :: 3.6
Classifier: Programming Language :: Python :: 3.7
Classifier: Topic :: System :: Filesystems
Requires-Python: >=3.5
Requires-Dist: krbticket (>=1.0.5)
Requires-Dist: pyarrow
Provides-Extra: doc
Requires-Dist: sphinx ; extra == 'doc'
Requires-Dist: sphinx-rtd-theme ; extra == 'doc'
Provides-Extra: test
Requires-Dist: pytest ; extra == 'test'
Requires-Dist: flake8 ; extra == 'test'
Requires-Dist: autopep8 ; extra == 'test'
Requires-Dist: parameterized ; extra == 'test'
